pulse_cli/__init__.py
pulse_cli/cli.py
pulse_cli-1.0.1.dist-info/METADATA
pulse_cli-1.0.1.dist-info/WHEEL
pulse_cli-1.0.1.dist-info/entry_points.txt
pulse_cli-1.0.1.dist-info/top_level.txt
pulse_cli-1.0.1.dist-info/RECORD
